{"country": "World", "report_year": 2019, "file_path": "c:\\Users\\alfon\\git\\export_control_analysis\\trade_analysis_pdfs\\2573-2019-statistical-analysis-of-u-s-trade-with-the-world.pdf", "export_balance": {"country": "US", "export_value": [1621.87, 1503.33, 1451.5, 1546.47, 1665.69, 1643.16], "import_value": [2356.36, 2248.81, 2186.79, 2339.88, 2537.73, 2497.53], "report_year": 2019, "year": [2014, 2015, 2016, 2017, 2018, 2019]}, "commodities": {"commodities_traded_export_percentage": [8.6, 12.8, 15.6, 2.2, 1.7, 4.3, 4.1, 23.1, 16.7, 5.7, 0.4, 1.2, 0.8, 2.9], "commodities_traded_import_percentage": [6.3, 8.3, 13.7, 1.7, 5.9, 3.2, 5.1, 28.7, 13.8, 4.1, 0.1, 4.1, 0.5, 4.5], "commodities_traded_type": ["Agriculture", "Minerals", "Chemicals, Plastics, Leather", "Wood Products", "Textiles and Footwear", "Stone, Glass, & Semiprecious Metals", "Base metals", "Machinery", "Transportation", "Optical, Measuring, Medical or Other Instruments", "Arms & Ammunition", "Miscellaneous Manufactured Items", "Art & Antiques", "Special Items"], "country": "US", "report_year": 2019}, "regulatory_authority": {"country": "US", "regulatory_authority_600_series": [0.3, 0.0, 0.0, 0.0, 0.3], "regulatory_authority_bis_license": [6.3, 6.0, 6.4, 6.4, 6.3], "regulatory_authority_bis_license_exception": [16.7, 20.4, 20.1, 16.7, 16.7], "regulatory_authority_department_of_commerce_values": [9.7, 9.8, 9.7, 9.7, 9.7], "regulatory_authority_department_of_state_values": [], "regulatory_authority_nlr_not_reporting_eccn": [], "regulatory_authority_nlr_reporting_ear99": [], "regulatory_authority_nlr_reporting_eccn": [198.6, 199.0, 199.0, 199.0, 198.6], "regulatory_authority_other_usg_agencies_values": [], "regulatory_authority_years": [2015, 2016, 2017, 2018, 2019], "report_year": 2019}, "country_chart": {"country": "US", "reasons_for_control": ["ML1", "ML2", "ML3", "ML4", "ML5", "ML6", "ML7", "ML8", "ML9", "ML10", "ML11", "ML12", "ML13", "ML14", "ML15", "ML16", "ML17", "ML18", "ML19", "ML20", "ML21", "ML22", "ML23", "ML24", "ML25", "ML26", "ML27", "ML28", "ML29", "ML30", "ML31", "ML32", "ML33", "ML34", "ML35", "ML36", "ML37", "ML38", "ML39", "ML40", "ML41", "ML42", "ML43", "ML44", "ML45", "ML46", "ML47", "ML48", "ML49", "ML50", "ML51", "ML52", "ML53", "ML54", "ML55", "ML56", "ML57", "ML58", "ML59", "ML60", "ML61", "ML62", "ML63", "ML64", "ML65", "ML66", "ML67", "ML68", "ML69", "ML70", "ML71", "ML72", "ML73", "ML74", "ML75", "ML76", "ML77", "ML78", "ML79", "ML80", "ML81", "ML82", "ML83", "ML84", "ML85", "ML86", "ML87", "ML88", "ML89", "ML90", "ML91", "ML92", "ML93", "ML94", "ML95", "ML96", "ML97", "ML98", "ML99", "ML100"], "report_year": 2019}, "top_eccn_by_value": {"country": "US", "report_year": 2019, "top_eccn_value_exceptions_descriptions": ["Systems/Equip./Integrated Circuits for Info Sec", "Military Aircraft and Related Commodities", "No ECCN is required for License Exceptions TMP*", "Items subject to the EAR that are not elsewhere controlled", "Military Gas Turbine Engines and Related Commodities", "Aircraft N.E.S. and Gas Turbine Engines not Controlled by 9A001 or 9A101...", "Electronic Components", "Military Electronics", "\"Software\" as follows (see List of Items Controlled)", "\"Information Security\" Test, Inspection and \"Production\" Equipment"], "top_eccn_value_exceptions_eccn_codes": ["5A002", "9A610", "No ECCN", "EAR99", "9A619", "9A991", "3A001", "3A611", "5D002", "5B002"], "top_eccn_value_licensed_descriptions": ["Military Aircraft and Related Commodities", "Spacecraft and Related Commodities", "Military Gas Turbine Engines and Related Commodities", "Military Electronics", "Ground Vehicles and Related Commodities", "Instrumentation, Navigation Equip./Systems Not", "Aero Gas Turbine Engines", "Acoustic Systems, Equipment and \"Components\"", "Inertial Navigation Systems (Gimballed/Strapdown)", "Systems/Equip./Integrated Circuits for Info Sec"], "top_eccn_value_licensed_eccn_codes": ["9A610", "9A515", "9A619", "3A611", "0A606", "7A103", "9A001", "6A001", "7A003", "5A002"], "top_eccn_value_nlr_with_eccn_descriptions": ["Aircraft N.E.S. and Gas Turbine Engines not Controlled by 9A001 or 9A101...", "Equipment not controlled by 5A002", "Telecommunication Equip. Not Controlled by 5A001", "Computers Not Controlled By 4A001 or 4A003", "Other Navigation Direction Finding Equip. ... Not Controlled under 7A003", "Other Mfg/Test Equip. Not Controlled By 3B", "Electronic Devices and \"Components\" not controlled by 3A001", "Equip. for the Inspection/Testing of Components not Controlled by 3B002", "Specific Processing Equip., N.E.S.", "Specific Processing Equip., N.E.S"], "top_eccn_value_nlr_with_eccn_eccn_codes": ["9A991", "5A992", "5A991", "4A994", "7A994", "3B991", "3A991", "3A992", "2B999", "3A999"]}, "top_eccn_by_count": {"country": "US", "report_year": 2019, "top_eccn_count_exceptions_descriptions": ["Systems/Equip./Integrated Circuits for Info Sec", "Military Aircraft and Related Commodities", "No ECCN is required for License Exceptions TMP*", "Items subject to the EAR that are not elsewhere controlled", "Military Gas Turbine Engines and Related Commodities", "Aircraft N.E.S. and Gas Turbine Engines not Controlled by 9A001 or 9A101...", "Electronic Components", "Military Electronics", "\"Software\" as follows (see List of Items Controlled)", "\"Information Security\" Test, Inspection and \"Production\" Equipment"], "top_eccn_count_exceptions_eccn_codes": ["5A002", "9A610", "No ECCN", "EAR99", "9A619", "9A991", "3A001", "3A611", "5D002", "5B002"], "top_eccn_count_licensed_descriptions": ["Military Aircraft and Related Commodities", "Military Gas Turbine Engines and Related Commodities", "Pressure Transducers", "Military Electronics", "Ground Vehicles and Related Commodities", "Optical Sighting Devices for Firearms", "Chemical Manufacturing Facilities and Equip.", "Instrumentation, Navigation Equip./Systems Not", "Shotguns, Buckshot, Shotgun Shells", "Systems/Equip./Integrated Circuits for Info Sec"], "top_eccn_count_licensed_eccn_codes": ["9A610", "9A619", "2B230", "3A611", "0A606", "0A987", "2B350", "7A103", "0A984", "5A002"], "top_eccn_count_nlr_with_eccn_descriptions": ["Aircraft N.E.S. and Gas Turbine Engines not Controlled by 9A001 or 9A101...", "Equipment not controlled by 5A002", "Telecommunication Equip. Not Controlled by 5A001", "Computers Not Controlled By 4A001 or 4A003", "Other Navigation Direction Finding Equip. ... Not Controlled under 7A003", "Other Mfg/Test Equip. Not Controlled By 3B", "Electronic Devices and \"Components\" not controlled by 3A001", "General Purpose Electronic Equip. Note Controlled by 3A002", "Specific Processing Equip., N.E.S.", "Specific Processing Equip., N.E.S"], "top_eccn_count_nlr_with_eccn_eccn_codes": ["9A991", "5A992", "5A991", "4A994", "7A994", "3B991", "3A991", "3A992", "2B999", "3A999"]}, "export_license": {"country": "US", "export_applications_approved": [32248, 29581, 31027, 29869, 29347], "export_applications_approved_value": [519994.3, 210298.3, 318108.2, 252186.8, 123001.0], "export_applications_available_years": [2015, 2016, 2017, 2018, 2019], "export_applications_average_processing_time": [22, 23, 18, 19, 23], "export_applications_deeemed_export_license_approved": [1124], "export_applications_deeemed_export_license_denied": [3], "export_applications_deeemed_export_license_rwa": [43], "export_applications_denied": [311, 301, 277, 264, 370], "export_applications_denied_value": [9315.6, 455.5, 666.0, 246.3, 421.6], "export_applications_rwa": [5700, 4680, 4994, 4548, 4400], "export_applications_rwa_value": [49926.4, 24685.8, 64333.6, 16392.8, 35585.7], "report_year": 2019}}